stir/CKA_minibatch.py
stir/CKA_pytorch.py
stir/__init__.py
stir/helper.py
stir/plot_helper.py
stir/stir.py
stir/attack/attack_steps.py
stir/attack/attacker.py
stir/attack/losses.py
stir/model/data_augmentation.py
stir/model/dataset_subsampler.py
stir/model/datasets.py
stir/model/defaults.py
stir/model/loaders.py
stir/model/model_utils.py
stir/model/train.py
stir/model/train_model.py
stir/model/cifar_models/__init__.py
stir/model/cifar_models/models.py
stir/model/cifar_models/resnet.py
stir/model/cifar_models/vgg.py
stir/model/tools/constants.py
stir/model/tools/custom_modules.py
stir/model/tools/folder.py
stir/model/tools/helpers.py
stir/model/tools/image_object.py
stir/model/tools/openimgs_helpers.py
stir_invariance-0.0.dist-info/LICENSE.md
stir_invariance-0.0.dist-info/METADATA
stir_invariance-0.0.dist-info/WHEEL
stir_invariance-0.0.dist-info/top_level.txt
stir_invariance-0.0.dist-info/RECORD
