Metadata-Version: 2.1
Name: stir-invariance
Version: 0.0
Summary: STIR -- shared invariance measure
Home-page: https://github.com/nvedant07/STIR
Author: Vedant Nanda
Author-email: vedant@cs.umd.edu
Classifier: Programming Language :: Python :: 3
Classifier: Programming Language :: Python :: 3.8
Classifier: License :: OSI Approved :: Apache Software License
Classifier: Operating System :: OS Independent
Classifier: Development Status :: 4 - Beta
License-File: LICENSE.md
Requires-Dist: torch (>=1.8.1)
Requires-Dist: torchvision (>=0.9.1)
Requires-Dist: numpy (>=1.22.0)
Requires-Dist: scipy (>=1.0.1)
Requires-Dist: tqdm (>=4.56.0)
Requires-Dist: matplotlib (>=3.2.2)
Requires-Dist: matplotlib-venn (>=0.11.6)
Requires-Dist: seaborn (>=0.11.0)
Requires-Dist: joblib (>=0.17.0)
Requires-Dist: dill (>=0.3.3)
Requires-Dist: scikit-learn (>=0.23.2)
Requires-Dist: Pillow (>=9.0.1)
